fuzzy_cmeans/__init__.py
fuzzy_cmeans/fuzzy_cmeans.py
scikit_fuzzy_c_means-0.1.3.dist-info/LICENSE
scikit_fuzzy_c_means-0.1.3.dist-info/METADATA
scikit_fuzzy_c_means-0.1.3.dist-info/WHEEL
scikit_fuzzy_c_means-0.1.3.dist-info/RECORD
