Metadata-Version: 2.1
Name: scikit-fuzzy-c-means
Version: 0.1.3
Summary: fuzzy c-means machine learnnig algorithm in scikit-learn style code
Home-page: https://github.com/sageteamorg/scikit-fuzzy-c-means
License: BSD 3-Clause License
Author: Sepehr Akbarzadeh
Author-email: sa.goldeneagle@gmail.com
Requires-Python: >=3.10
Classifier: Development Status :: 5 - Production/Stable
Classifier: Intended Audience :: Developers
Classifier: Intended Audience :: Science/Research
Classifier: License :: OSI Approved :: BSD License
Classifier: License :: Other/Proprietary License
Classifier: Operating System :: MacOS
Classifier: Operating System :: Microsoft :: Windows
Classifier: Operating System :: POSIX
Classifier: Operating System :: Unix
Classifier: Programming Language :: C
Classifier: Programming Language :: Python
Classifier: Programming Language :: Python :: 3
Classifier: Programming Language :: Python :: 3.10
Classifier: Programming Language :: Python :: 3.11
Classifier: Programming Language :: Python :: 3.12
Classifier: Programming Language :: Python :: 3.13
Classifier: Programming Language :: Python :: Implementation :: CPython
Classifier: Topic :: Scientific/Engineering
Classifier: Topic :: Software Development
Requires-Dist: commitizen (>=3.31.0,<4.0.0)
Requires-Dist: scikit-learn (>=1.5.2,<2.0.0)
Requires-Dist: scipy (>=1.14.1,<2.0.0)
Project-URL: Documentation, https://scikit-fuzzy-c-means.readthedocs.io/en/latest/
Project-URL: Issues, https://github.com/sageteamorg/scikit-fuzzy-c-means/issues
Project-URL: Repository, https://github.com/sageteamorg/scikit-fuzzy-c-means
